{"fixed1bottom": {"pmin": [5e-08, 2.5e-08, -2e-08], "pmax": [1.525e-07, 7.75e-08, -1.75e-08], "dims": ["x", "y", "z"], "units": ["m", "m", "m"], "tolerance_factor": 1e-12}, "fixed1bottomspike": {"pmin": [9.25e-08, 4.25e-08, -2e-08], "pmax": [1.1e-07, 6e-08, -1e-08], "dims": ["x", "y", "z"], "units": ["m", "m", "m"], "tolerance_factor": 1e-12}, "fixed1top": {"pmin": [5e-08, 2.5e-08, 7.5e-09], "pmax": [1.525e-07, 7.75e-08, 1e-08], "dims": ["x", "y", "z"], "units": ["m", "m", "m"], "tolerance_factor": 1e-12}, "fixed1topspike": {"pmin": [9.25e-08, 4.25e-08, 5e-09], "pmax": [1.1e-07, 6e-08, 1e-08], "dims": ["x", "y", "z"], "units": ["m", "m", "m"], "tolerance_factor": 1e-12}, "free1bottom": {"pmin": [0.0, 0.0, -2e-08], "pmax": [2e-07, 1e-07, 0.0], "dims": ["x", "y", "z"], "units": ["m", "m", "m"], "tolerance_factor": 1e-12}, "free1top": {"pmin": [0.0, 0.0, 0.0], "pmax": [2e-07, 1e-07, 1e-08], "dims": ["x", "y", "z"], "units": ["m", "m", "m"], "tolerance_factor": 1e-12}, "free2bottom": {"pmin": [2e-07, 0.0, -2e-08], "pmax": [4e-07, 1e-07, 0.0], "dims": ["x", "y", "z"], "units": ["m", "m", "m"], "tolerance_factor": 1e-12}, "free2top": {"pmin": [2e-07, 0.0, 0.0], "pmax": [4e-07, 1e-07, 1e-08], "dims": ["x", "y", "z"], "units": ["m", "m", "m"], "tolerance_factor": 1e-12}, "fixed3bottom": {"pmin": [4.5e-07, 2.5e-08, -2e-08], "pmax": [5.525e-07, 7.75e-08, -1.75e-08], "dims": ["x", "y", "z"], "units": ["m", "m", "m"], "tolerance_factor": 1e-12}, "fixed3bottomspike": {"pmin": [4.925e-07, 4.25e-08, -2e-08], "pmax": [5.1e-07, 6e-08, -1e-08], "dims": ["x", "y", "z"], "units": ["m", "m", "m"], "tolerance_factor": 1e-12}, "fixed3top": {"pmin": [4.5e-07, 2.5e-08, 7.5e-09], "pmax": [5.525e-07, 7.75e-08, 1e-08], "dims": ["x", "y", "z"], "units": ["m", "m", "m"], "tolerance_factor": 1e-12}, "fixed3topspike": {"pmin": [4.925e-07, 4.25e-08, 5e-09], "pmax": [5.1e-07, 6e-08, 1e-08], "dims": ["x", "y", "z"], "units": ["m", "m", "m"], "tolerance_factor": 1e-12}, "free3bottom": {"pmin": [4e-07, 0.0, -2e-08], "pmax": [6e-07, 1e-07, 0.0], "dims": ["x", "y", "z"], "units": ["m", "m", "m"], "tolerance_factor": 1e-12}, "free3top": {"pmin": [4e-07, 0.0, 0.0], "pmax": [6e-07, 1e-07, 1e-08], "dims": ["x", "y", "z"], "units": ["m", "m", "m"], "tolerance_factor": 1e-12}, "fixed4bottom": {"pmin": [6.5e-07, 2.5e-08, -2e-08], "pmax": [7.525e-07, 7.75e-08, -1.75e-08], "dims": ["x", "y", "z"], "units": ["m", "m", "m"], "tolerance_factor": 1e-12}, "fixed4bottomspike": {"pmin": [6.925e-07, 4.25e-08, -2e-08], "pmax": [7.1e-07, 6e-08, -1e-08], "dims": ["x", "y", "z"], "units": ["m", "m", "m"], "tolerance_factor": 1e-12}, "fixed4top": {"pmin": [6.5e-07, 2.5e-08, 7.5e-09], "pmax": [7.525e-07, 7.75e-08, 1e-08], "dims": ["x", "y", "z"], "units": ["m", "m", "m"], "tolerance_factor": 1e-12}, "fixed4topspike": {"pmin": [6.925e-07, 4.25e-08, 5e-09], "pmax": [7.1e-07, 6e-08, 1e-08], "dims": ["x", "y", "z"], "units": ["m", "m", "m"], "tolerance_factor": 1e-12}, "free4bottom": {"pmin": [6e-07, 0.0, -2e-08], "pmax": [8e-07, 1e-07, 0.0], "dims": ["x", "y", "z"], "units": ["m", "m", "m"], "tolerance_factor": 1e-12}, "free4top": {"pmin": [6e-07, 0.0, 0.0], "pmax": [8e-07, 1e-07, 1e-08], "dims": ["x", "y", "z"], "units": ["m", "m", "m"], "tolerance_factor": 1e-12}, "fixed5bottom": {"pmin": [8.5e-07, 2.5e-08, -2e-08], "pmax": [9.525e-07, 7.75e-08, -1.75e-08], "dims": ["x", "y", "z"], "units": ["m", "m", "m"], "tolerance_factor": 1e-12}, "fixed5bottomspike": {"pmin": [8.925e-07, 4.25e-08, -2e-08], "pmax": [9.1e-07, 6e-08, -1e-08], "dims": ["x", "y", "z"], "units": ["m", "m", "m"], "tolerance_factor": 1e-12}, "fixed5top": {"pmin": [8.5e-07, 2.5e-08, 7.5e-09], "pmax": [9.525e-07, 7.75e-08, 1e-08], "dims": ["x", "y", "z"], "units": ["m", "m", "m"], "tolerance_factor": 1e-12}, "fixed5topspike": {"pmin": [8.925e-07, 4.25e-08, 5e-09], "pmax": [9.1e-07, 6e-08, 1e-08], "dims": ["x", "y", "z"], "units": ["m", "m", "m"], "tolerance_factor": 1e-12}, "free5bottom": {"pmin": [8e-07, 0.0, -2e-08], "pmax": [1e-06, 1e-07, 0.0], "dims": ["x", "y", "z"], "units": ["m", "m", "m"], "tolerance_factor": 1e-12}, "free5top": {"pmin": [8e-07, 0.0, 0.0], "pmax": [1e-06, 1e-07, 1e-08], "dims": ["x", "y", "z"], "units": ["m", "m", "m"], "tolerance_factor": 1e-12}, "fixed6bottom": {"pmin": [1.05e-06, 2.5e-08, -2e-08], "pmax": [1.1525e-06, 7.75e-08, -1.75e-08], "dims": ["x", "y", "z"], "units": ["m", "m", "m"], "tolerance_factor": 1e-12}, "fixed6bottomspike": {"pmin": [1.0925e-06, 4.25e-08, -2e-08], "pmax": [1.11e-06, 6e-08, -1e-08], "dims": ["x", "y", "z"], "units": ["m", "m", "m"], "tolerance_factor": 1e-12}, "fixed6top": {"pmin": [1.05e-06, 2.5e-08, 7.5e-09], "pmax": [1.1525e-06, 7.75e-08, 1e-08], "dims": ["x", "y", "z"], "units": ["m", "m", "m"], "tolerance_factor": 1e-12}, "fixed6topspike": {"pmin": [1.0925e-06, 4.25e-08, 5e-09], "pmax": [1.11e-06, 6e-08, 1e-08], "dims": ["x", "y", "z"], "units": ["m", "m", "m"], "tolerance_factor": 1e-12}, "free6bottom": {"pmin": [1e-06, 0.0, -2e-08], "pmax": [1.2e-06, 1e-07, 0.0], "dims": ["x", "y", "z"], "units": ["m", "m", "m"], "tolerance_factor": 1e-12}, "free6top": {"pmin": [1e-06, 0.0, 0.0], "pmax": [1.2e-06, 1e-07, 1e-08], "dims": ["x", "y", "z"], "units": ["m", "m", "m"], "tolerance_factor": 1e-12}, "free7bottom": {"pmin": [1.2e-06, 0.0, -2e-08], "pmax": [1.4e-06, 1e-07, 0.0], "dims": ["x", "y", "z"], "units": ["m", "m", "m"], "tolerance_factor": 1e-12}, "free7top": {"pmin": [1.2e-06, 0.0, 0.0], "pmax": [1.4e-06, 1e-07, 1e-08], "dims": ["x", "y", "z"], "units": ["m", "m", "m"], "tolerance_factor": 1e-12}, "free8bottom": {"pmin": [1.4e-06, 0.0, -2e-08], "pmax": [1.6e-06, 1e-07, 0.0], "dims": ["x", "y", "z"], "units": ["m", "m", "m"], "tolerance_factor": 1e-12}, "free8top": {"pmin": [1.4e-06, 0.0, 0.0], "pmax": [1.6e-06, 1e-07, 1e-08], "dims": ["x", "y", "z"], "units": ["m", "m", "m"], "tolerance_factor": 1e-12}}